{"api-guides_events.md":"CiGVxosq","api-guides_geometry.md":"DhKpmB_w","api-guides_instance.md":"BDmmLCJr","api-guides_layers.md":"DEdXl3DY","api-guides_legend.md":"0vm79iWc","api-guides_notifications.md":"D6lLXyNB","api-guides_panels.md":"B_cj3WIG","index.md":"nTdIWdin","introduction_instantiation.md":"BaJkOifX","introduction_library.md":"UpiPyCYG","introduction_setup.md":"BycyF_eY","overview.md":"C3-RHEUQ","resources_core-classes.md":"BRwRjnKr","resources_focus-list.md":"vbDmZxZA","resources_migration_api-migration.md":"B-lZ2fwT","resources_migration_migration-notes.md":"UKhY-b5K","resources_store.md":"_t8u6jbE","resources_tooltips.md":"CXVgb34Y","typedoc-readme.md":"B5VcOtpX","using-ramp4_config-language.md":"BJVlPBsP","using-ramp4_default-setup.md":"DYsZ5DKm","using-ramp4_fixture-overview.md":"cAKnLOhI","using-ramp4_fixtures_appbar.md":"Cg9wQUh9","using-ramp4_fixtures_custom-fixtures.md":"Bjg4aAnx","using-ramp4_fixtures_details.md":"DtNwEjpB","using-ramp4_fixtures_draw-tools.md":"JAobWRx-","using-ramp4_fixtures_extentguard.md":"B2WJNAJd","using-ramp4_fixtures_geosearch.md":"D816p4GC","using-ramp4_fixtures_grid.md":"CLiaDSh9","using-ramp4_fixtures_layer-settings.md":"DwGQvQ4H","using-ramp4_fixtures_legend.md":"LN0r0THI","using-ramp4_incompatibility.md":"BfBWAYYf","using-ramp4_layer-overview.md":"DeIMYZaW","using-ramp4_layers_additional-layer-sections.md":"qjR0WgnF","using-ramp4_layers_basic-properties.md":"BH71LXaF","using-ramp4_layers_fancy-properties.md":"DpLnfCqN","using-ramp4_layers_required-properties.md":"CTbXTrnW","using-ramp4_layers_sublayer-properties.md":"DRqafABV"}
